walp/__init__.py
walp/__main__.py
walp/dirs.dat
walp/walp.py
walp/scripts/collection.py
walp/scripts/engine.py
walp/scripts/image.py
walp/scripts/preset.py
walp/scripts/state.py
walp/utils/defaults.py
walp/utils/parser.py
walp/utils/storage.py
walp-0.0.3.dist-info/METADATA
walp-0.0.3.dist-info/WHEEL
walp-0.0.3.dist-info/entry_points.txt
walp-0.0.3.dist-info/top_level.txt
walp-0.0.3.dist-info/RECORD
