Metadata-Version: 2.1
Name: walp
Version: 0.0.3
Summary: A command-line wallpaper manager
Home-page: https://github.com/rhe4n/walp
Author: rhean
Author-email: rheandhont@gmail.com
License: UNKNOWN
Platform: UNKNOWN
Requires-Dist: click (>=8.0.3)
Requires-Dist: appdirs (>=1.4.4)
Requires-Dist: pillow (>=9.0.0)
